clock/__init__.py
clock/main.py
clockz_cli-0.3.2.dist-info/METADATA
clockz_cli-0.3.2.dist-info/WHEEL
clockz_cli-0.3.2.dist-info/entry_points.txt
clockz_cli-0.3.2.dist-info/top_level.txt
clockz_cli-0.3.2.dist-info/RECORD
