Metadata-Version: 2.1
Name: clockz-cli
Version: 0.3.2
Requires-Dist: click
Requires-Dist: pynput
